{
  "imeis": [
    {
      "plates": "48AS9N",
      "eco": "TR-307/48AS9N",
      "vin": "",
      "imei": "867869060102464"
    },
    {
      "plates": "42AS3A",
      "eco": "M-205/42AS3A",
      "vin": "",
      "imei": "867869060126232"
    },
    {
      "plates": "77BC3A",
      "eco": "TR-317/ 77BC3A",
      "vin": "",
      "imei": "867869060114584"
    },
    {
      "plates": "LF58634",
      "eco": "C-106/LF58634",
      "vin": "",
      "imei": "867869060121258"
    },
    {
      "plates": "90AS2M",
      "eco": "M-204/90AS2M",
      "vin": "",
      "imei": "867869060117652"
    },
    {
      "plates": "98BB2J",
      "eco": "TR-315 / 98BB2J",
      "vin": "",
      "imei": "867869060559127"
    },
    {
      "plates": "LE47346",
      "eco": "M-208/LE47346",
      "vin": "",
      "imei": "867869060396934"
    },
    {
      "plates": "39AZ6W",
      "eco": "TR-312 /39AZ6W",
      "vin": "",
      "imei": "867869060836228"
    },
    {
      "plates": "63AX2S",
      "eco": "M-206/63AX2S",
      "vin": "",
      "imei": "867869060102928"
    },
    {
      "plates": "LE75388",
      "eco": "C-110",
      "vin": "",
      "imei": "867869060121142"
    },
    {
      "plates": "LG11069",
      "eco": "C-107/LG11069",
      "vin": "",
      "imei": "867869060244787"
    },
    {
      "plates": "609DN4",
      "eco": "C-100",
      "vin": "",
      "imei": "867869060114337"
    },
    {
      "plates": "41AX4R",
      "eco": "M-207/41AX4R",
      "vin": "",
      "imei": "867869060846169"
    },
    {
      "plates": "87AZ8U",
      "eco": "TR-314/87AZ8U",
      "vin": "",
      "imei": "867869060549003"
    },
    {
      "plates": "08AZ1R",
      "eco": "TR-518/PERM/08AZ1R",
      "vin": "CN377910",
      "imei": "867869060241155"
    },
    {
      "plates": "07BC5C",
      "eco": "TR-316 / 07BC5C",
      "vin": "",
      "imei": "867869060124336"
    },
    {
      "plates": "Sin placas",
      "eco": "Meitrack T366G",
      "vin": "",
      "imei": "867869011111111"
    },
    {
      "plates": "96AT9K",
      "eco": "TR-309 / 96AT9K",
      "vin": "KAD40X28F813853",
      "imei": "867869060102324"
    },
    {
      "plates": "95BF2A",
      "eco": "TR-319",
      "vin": "3HSDJAPTXHN577777",
      "imei": "867869060123049"
    },
    {
      "plates": "45AV5C",
      "eco": "TR-310",
      "vin": "1FUBA5CK89DAF5938",
      "imei": "867869060114881"
    },
    {
      "plates": "LF81277",
      "eco": "C-109",
      "vin": "1FTYR1CMOJKB18939",
      "imei": "867869060103637"
    },
    {
      "plates": "LE74630",
      "eco": "C-103",
      "vin": "1",
      "imei": "867869060122991"
    },
    {
      "plates": "PBW1466",
      "eco": "C-108/PBW1466",
      "vin": "WV1CAASE0HX001330",
      "imei": "867869060121670"
    },
    {
      "plates": "15AX8W",
      "eco": "TR-311/15AX8W",
      "vin": "sn",
      "imei": "867869060550233"
    },
    {
      "plates": "54BE4Y",
      "eco": "TR-320",
      "vin": "s!",
      "imei": "867869060123916"
    },
    {
      "plates": "LF21168",
      "eco": "C11",
      "vin": "VF3YDUMF6M2N08745",
      "imei": "867869060121043"
    }
  ]
}