{
  "imeis": [
    {
      "original": "867869060395167",
      "spoofed": "472480240404247"
    },
    {
      "original": "867869060126323",
      "spoofed": "472480240404213"
    },
    {
      "original": "864352044938447",
      "spoofed": "472480240404080"
    },
    {
      "original": "867869060122363",
      "spoofed": "472480240404221"
    },
    {
      "original": "867869060396108",
      "spoofed": "472480240404254"
    },
    {
      "original": "864352046160867",
      "spoofed": "472480240404106"
    },
    {
      "original": "867869060332228",
      "spoofed": "472480240404163"
    },
    {
      "original": "864606046273347",
      "spoofed": "472480240404056"
    },
    {
      "original": "867869060395332",
      "spoofed": "472480240404239"
    },
    {
      "original": "867869060273232",
      "spoofed": "472480240404171"
    },
    {
      "original": "864352044921401",
      "spoofed": "472480240404155"
    },
    {
      "original": "864507038431531",
      "spoofed": "472480240404064"
    },
    {
      "original": "864606047647689",
      "spoofed": "472480240404015"
    },
    {
      "original": "867869060389350",
      "spoofed": "472480240404122"
    },
    {
      "original": "868998033136488",
      "spoofed": "472480240404072"
    },
    {
      "original": "864606045017091",
      "spoofed": "472480240404205"
    },
    {
      "original": "868998030322131",
      "spoofed": "472480240404031"
    },
    {
      "original": "867869060396751",
      "spoofed": "472480240404114"
    },
    {
      "original": "864507035846483",
      "spoofed": "472480240404098"
    },
    {
      "original": "867869060120193",
      "spoofed": "472480240404197"
    },
    {
      "original": "864352043129279",
      "spoofed": "472480240404189"
    },
    {
      "original": "868998035941901",
      "spoofed": "472480240404023"
    },
    {
      "original": "868998036792345",
      "spoofed": "472480240404049"
    },
    {
      "original": "864606046270962",
      "spoofed": "472480240404148"
    },
    {
      "original": "867869061826871",
      "spoofed": "472480240404130"
    },
    {
      "original": "864352047219654",
      "spoofed": "472480240404007"
    }
  ]
}